COPYING
MANIFEST.in
README.rst
bootstrap.py
buildout.cfg
setup.py
docs/conf.py
docs/index.rst
xbob/__init__.py
xbob.mlp.lbfgs.egg-info/PKG-INFO
xbob.mlp.lbfgs.egg-info/SOURCES.txt
xbob.mlp.lbfgs.egg-info/dependency_links.txt
xbob.mlp.lbfgs.egg-info/entry_points.txt
xbob.mlp.lbfgs.egg-info/namespace_packages.txt
xbob.mlp.lbfgs.egg-info/requires.txt
xbob.mlp.lbfgs.egg-info/top_level.txt
xbob/mlp/__init__.py
xbob/mlp/lbfgs/__init__.py
xbob/mlp/lbfgs/test.py
xbob/mlp/lbfgs/trainer.py